pytest_mark_integration/__init__.py
pytest_mark_integration/plugin.py
pytest_mark_integration-1.0.1.dist-info/METADATA
pytest_mark_integration-1.0.1.dist-info/WHEEL
pytest_mark_integration-1.0.1.dist-info/entry_points.txt
pytest_mark_integration-1.0.1.dist-info/licenses/LICENSE
pytest_mark_integration-1.0.1.dist-info/RECORD
