Metadata-Version: 2.4
Name: pytest-mark-integration
Version: 1.0.1
Summary: Pytest plugin for automatic integration test marking and management
Project-URL: Bug Tracker, https://github.com/xykong/pytest-mark-integration/issues
Project-URL: Changelog, https://github.com/xykong/pytest-mark-integration/blob/main/CHANGELOG.md
Project-URL: Documentation, https://github.com/xykong/pytest-mark-integration#readme
Project-URL: Homepage, https://github.com/xykong/pytest-mark-integration
Project-URL: Repository, https://github.com/xykong/pytest-mark-integration
Author-email: "xy.kong" <xy.kong@gmail.com>
Maintainer-email: "xy.kong" <xy.kong@gmail.com>
License: Apache-2.0
License-File: LICENSE
Keywords: integration,plugin,pytest,test-automation,testing
Classifier: Development Status :: 4 - Beta
Classifier: Framework :: Pytest
Classifier: Intended Audience :: Developers
Classifier: License :: OSI Approved :: Apache Software License
Classifier: Operating System :: OS Independent
Classifier: Programming Language :: Python
Classifier: Programming Language :: Python :: 3
Classifier: Programming Language :: Python :: 3.10
Classifier: Programming Language :: Python :: 3.11
Classifier: Programming Language :: Python :: 3.12
Classifier: Programming Language :: Python :: 3.13
Classifier: Programming Language :: Python :: 3.14
Classifier: Topic :: Software Development :: Quality Assurance
Classifier: Topic :: Software Development :: Testing
Requires-Python: >=3.10
Requires-Dist: pytest>=7.0.0
Provides-Extra: dev
Requires-Dist: black>=23.0.0; extra == 'dev'
Requires-Dist: mypy>=1.0.0; extra == 'dev'
Requires-Dist: pytest-cov>=4.0.0; extra == 'dev'
Requires-Dist: pytest-timeout>=2.0.0; extra == 'dev'
Requires-Dist: ruff>=0.1.0; extra == 'dev'
